arkwaifu_2x/__init__.py
arkwaifu_2x/app.py
arkwaifu_2x/arkwaifu/__init__.py
arkwaifu_2x/arkwaifu/models.py
arkwaifu_2x/real_esrgan/__init__.py
arkwaifu_2x/real_esrgan/models/realesr-animevideov3-x2.bin
arkwaifu_2x/real_esrgan/models/realesr-animevideov3-x2.param
arkwaifu_2x/real_esrgan/models/realesr-animevideov3-x3.bin
arkwaifu_2x/real_esrgan/models/realesr-animevideov3-x3.param
arkwaifu_2x/real_esrgan/models/realesr-animevideov3-x4.bin
arkwaifu_2x/real_esrgan/models/realesr-animevideov3-x4.param
arkwaifu_2x/real_esrgan/models/realesrgan-x4plus-anime.bin
arkwaifu_2x/real_esrgan/models/realesrgan-x4plus-anime.param
arkwaifu_2x/real_esrgan/models/realesrgan-x4plus.bin
arkwaifu_2x/real_esrgan/models/realesrgan-x4plus.param
arkwaifu_2x/real_esrgan/realesrgan-ncnn-vulkan.exe
arkwaifu_2x/real_esrgan/vcomp140.dll
arkwaifu_2x/real_esrgan/vcomp140d.dll
arkwaifu_2x-1.1.0.dist-info/entry_points.txt
arkwaifu_2x-1.1.0.dist-info/LICENSE
arkwaifu_2x-1.1.0.dist-info/METADATA
arkwaifu_2x-1.1.0.dist-info/WHEEL
arkwaifu_2x-1.1.0.dist-info/RECORD
