Metadata-Version: 2.1
Name: arkwaifu-2x
Version: 1.1.0
Summary: A CLI management tool for Arkwaifu.
License: MIT
Author: Flandia Yingman
Author-email: flandia_yingm@hotmail.com
Requires-Python: >=3.11,<4.0
Classifier: License :: OSI Approved :: MIT License
Classifier: Programming Language :: Python :: 3
Classifier: Programming Language :: Python :: 3.11
Requires-Dist: inquirer (>=3.1.3,<4.0.0)
Requires-Dist: parse (>=1.19.1,<2.0.0)
Requires-Dist: pillow (>=10.0.0,<11.0.0)
Requires-Dist: requests (>=2.31.0,<3.0.0)
Requires-Dist: rich (>=13.4.2,<14.0.0)
